igeAutoTest.cp39-win_amd64.pyd
igeAutoTest-0.0.4.dist-info/LICENSE
igeAutoTest-0.0.4.dist-info/METADATA
igeAutoTest-0.0.4.dist-info/WHEEL
igeAutoTest-0.0.4.dist-info/top_level.txt
igeAutoTest-0.0.4.dist-info/RECORD
